{"total":118,"hasNext":true,"subjects":[{"rating":{"max":10,"average":0,"stars":"00","min":0},"genres":["剧情"],"title":"让爱活下去","casts":[{"alt":"https://movie.douban.com/celebrity/1318160/","avatars":{"small":"https://img3.doubanio.com/img/celebrity/small/42304.jpg","large":"https://img3.doubanio.com/img/celebrity/large/42304.jpg","medium":"https://img3.doubanio.com/img/celebrity/medium/42304.jpg"},"name":"夏德俊","id":"1318160"},{"alt":"https://movie.douban.com/celebrity/1037023/","avatars":{"small":"https://img3.doubanio.com/img/celebrity/small/1696.jpg","large":"https://img3.doubanio.com/img/celebrity/large/1696.jpg","medium":"https://img3.doubanio.com/img/celebrity/medium/1696.jpg"},"name":"郑佩佩","id":"1037023"},{"alt":"https://movie.douban.com/celebrity/1337497/","avatars":{"small":"https://img3.doubanio.com/img/celebrity/small/u6TVWYdsWkcel_avatar_uploaded1389690964.21.jpg","large":"https://img3.doubanio.com/img/celebrity/large/u6TVWYdsWkcel_avatar_uploaded1389690964.21.jpg","medium":"https://img3.doubanio.com/img/celebrity/medium/u6TVWYdsWkcel_avatar_uploaded1389690964.21.jpg"},"name":"周诗璇","id":"1337497"}],"collect_count":21,"original_title":"让爱活下去","subtype":"movie","directors":[{"alt":"https://movie.douban.com/celebrity/1368145/","avatars":{"small":"https://img3.doubanio.com/img/celebrity/small/1493911003.22.jpg","large":"https://img3.doubanio.com/img/celebrity/large/1493911003.22.jpg","medium":"https://img3.doubanio.com/img/celebrity/medium/1493911003.22.jpg"},"name":"查文白","id":"1368145"}],"year":"2017","images":{"small":"https://img1.doubanio.com/view/movie_poster_cover/ipst/public/p2463057139.jpg","large":"https://img1.doubanio.com/view/movie_poster_cover/lpst/public/p2463057139.jpg","medium":"https://img1.doubanio.com/view/movie_poster_cover/spst/public/p2463057139.jpg"},"alt":"https://movie.douban.com/subject/26922911/","id":"26922911"},{"rating":{"max":10,"average":0,"stars":"00","min":0},"genres":["动作"],"title":"战狼2","casts":[{"alt":"https://movie.douban.com/celebrity/1000525/","avatars":{"small":"https://img3.doubanio.com/img/celebrity/small/39105.jpg","large":"https://img3.doubanio.com/img/celebrity/large/39105.jpg","medium":"https://img3.doubanio.com/img/celebrity/medium/39105.jpg"},"name":"吴京","id":"1000525"},{"alt":"https://movie.douban.com/celebrity/1100321/","avatars":{"small":"https://img1.doubanio.com/img/celebrity/small/1415801312.29.jpg","large":"https://img1.doubanio.com/img/celebrity/large/1415801312.29.jpg","medium":"https://img1.doubanio.com/img/celebrity/medium/1415801312.29.jpg"},"name":"弗兰克·格里罗","id":"1100321"},{"alt":"https://movie.douban.com/celebrity/1018743/","avatars":{"small":"https://img1.doubanio.com/img/celebrity/small/9409.jpg","large":"https://img1.doubanio.com/img/celebrity/large/9409.jpg","medium":"https://img1.doubanio.com/img/celebrity/medium/9409.jpg"},"name":"卢靖姗","id":"1018743"}],"collect_count":292,"original_title":"战狼2","subtype":"movie","directors":[{"alt":"https://movie.douban.com/celebrity/1000525/","avatars":{"small":"https://img3.doubanio.com/img/celebrity/small/39105.jpg","large":"https://img3.doubanio.com/img/celebrity/large/39105.jpg","medium":"https://img3.doubanio.com/img/celebrity/medium/39105.jpg"},"name":"吴京","id":"1000525"}],"year":"2017","images":{"small":"https://img3.doubanio.com/view/movie_poster_cover/ipst/public/p2485983612.jpg","large":"https://img3.doubanio.com/view/movie_poster_cover/lpst/public/p2485983612.jpg","medium":"https://img3.doubanio.com/view/movie_poster_cover/spst/public/p2485983612.jpg"},"alt":"https://movie.douban.com/subject/26363254/","id":"26363254"},{"rating":{"max":10,"average":0,"stars":"00","min":0},"genres":["剧情","历史"],"title":"建军大业","casts":[{"alt":"https://movie.douban.com/celebrity/1000572/","avatars":{"small":"https://img3.doubanio.com/img/celebrity/small/43.jpg","large":"https://img3.doubanio.com/img/celebrity/large/43.jpg","medium":"https://img3.doubanio.com/img/celebrity/medium/43.jpg"},"name":"刘烨","id":"1000572"},{"alt":"https://movie.douban.com/celebrity/1312699/","avatars":{"small":"https://img1.doubanio.com/img/celebrity/small/1414489207.88.jpg","large":"https://img1.doubanio.com/img/celebrity/large/1414489207.88.jpg","medium":"https://img1.doubanio.com/img/celebrity/medium/1414489207.88.jpg"},"name":"朱亚文","id":"1312699"},{"alt":"https://movie.douban.com/celebrity/1255860/","avatars":{"small":"https://img3.doubanio.com/img/celebrity/small/1415028529.74.jpg","large":"https://img3.doubanio.com/img/celebrity/large/1415028529.74.jpg","medium":"https://img3.doubanio.com/img/celebrity/medium/1415028529.74.jpg"},"name":"黄志忠","id":"1255860"}],"collect_count":190,"original_title":"建军大业","subtype":"movie","directors":[{"alt":"https://movie.douban.com/celebrity/1106979/","avatars":{"small":"https://img1.doubanio.com/img/celebrity/small/1403267018.07.jpg","large":"https://img1.doubanio.com/img/celebrity/large/1403267018.07.jpg","medium":"https://img1.doubanio.com/img/celebrity/medium/1403267018.07.jpg"},"name":"刘伟强","id":"1106979"}],"year":"2017","images":{"small":"https://img3.doubanio.com/view/movie_poster_cover/ipst/public/p2400883685.jpg","large":"https://img3.doubanio.com/view/movie_poster_cover/lpst/public/p2400883685.jpg","medium":"https://img3.doubanio.com/view/movie_poster_cover/spst/public/p2400883685.jpg"},"alt":"https://movie.douban.com/subject/26692823/","id":"26692823"},{"rating":{"max":10,"average":0,"stars":"00","min":0},"genres":["动画"],"title":"豆福传","casts":[{"alt":"https://movie.douban.com/celebrity/1280571/","avatars":{"small":"https://img3.doubanio.com/img/celebrity/small/10935.jpg","large":"https://img3.doubanio.com/img/celebrity/large/10935.jpg","medium":"https://img3.doubanio.com/img/celebrity/medium/10935.jpg"},"name":"陈佩斯","id":"1280571"},{"alt":"https://movie.douban.com/celebrity/1274438/","avatars":{"small":"https://img1.doubanio.com/img/celebrity/small/32977.jpg","large":"https://img1.doubanio.com/img/celebrity/large/32977.jpg","medium":"https://img1.doubanio.com/img/celebrity/medium/32977.jpg"},"name":"李立群","id":"1274438"},{"alt":"https://movie.douban.com/celebrity/1317669/","avatars":{"small":"https://img3.doubanio.com/img/celebrity/small/40762.jpg","large":"https://img3.doubanio.com/img/celebrity/large/40762.jpg","medium":"https://img3.doubanio.com/img/celebrity/medium/40762.jpg"},"name":"季冠霖","id":"1317669"}],"collect_count":98,"original_title":"豆福传","subtype":"movie","directors":[{"alt":"https://movie.douban.com/celebrity/1354805/","avatars":{"small":"https://img1.doubanio.com/img/celebrity/small/1455949404.39.jpg","large":"https://img1.doubanio.com/img/celebrity/large/1455949404.39.jpg","medium":"https://img1.doubanio.com/img/celebrity/medium/1455949404.39.jpg"},"name":"邹燚","id":"1354805"}],"year":"2017","images":{"small":"https://img3.doubanio.com/view/movie_poster_cover/ipst/public/p2462145010.jpg","large":"https://img3.doubanio.com/view/movie_poster_cover/lpst/public/p2462145010.jpg","medium":"https://img3.doubanio.com/view/movie_poster_cover/spst/public/p2462145010.jpg"},"alt":"https://movie.douban.com/subject/26705107/","id":"26705107"},{"rating":{"max":10,"average":0,"stars":"00","min":0},"genres":["喜剧","动画","冒险"],"title":"大耳朵图图之美食狂想曲","casts":[{"alt":"https://movie.douban.com/celebrity/1317642/","avatars":{"small":"https://img1.doubanio.com/img/celebrity/small/40719.jpg","large":"https://img1.doubanio.com/img/celebrity/large/40719.jpg","medium":"https://img1.doubanio.com/img/celebrity/medium/40719.jpg"},"name":"潘延","id":"1317642"},{"alt":"https://movie.douban.com/celebrity/1321911/","avatars":{"small":"https://img3.doubanio.com/img/celebrity/small/1357876944.24.jpg","large":"https://img3.doubanio.com/img/celebrity/large/1357876944.24.jpg","medium":"https://img3.doubanio.com/img/celebrity/medium/1357876944.24.jpg"},"name":"范楚绒","id":"1321911"},{"alt":"https://movie.douban.com/celebrity/1328393/","avatars":{"small":"https://img3.doubanio.com/img/celebrity/small/1498555461.54.jpg","large":"https://img3.doubanio.com/img/celebrity/large/1498555461.54.jpg","medium":"https://img3.doubanio.com/img/celebrity/medium/1498555461.54.jpg"},"name":"胡谦","id":"1328393"}],"collect_count":27,"original_title":"大耳朵图图之美食狂想曲","subtype":"movie","directors":[{"alt":"https://movie.douban.com/celebrity/1327328/","avatars":{"small":"https://img1.doubanio.com/img/celebrity/small/1381377742.7.jpg","large":"https://img1.doubanio.com/img/celebrity/large/1381377742.7.jpg","medium":"https://img1.doubanio.com/img/celebrity/medium/1381377742.7.jpg"},"name":"速达","id":"1327328"}],"year":"2017","images":{"small":"https://img3.doubanio.com/view/movie_poster_cover/ipst/public/p2490966346.jpg","large":"https://img3.doubanio.com/view/movie_poster_cover/lpst/public/p2490966346.jpg","medium":"https://img3.doubanio.com/view/movie_poster_cover/spst/public/p2490966346.jpg"},"alt":"https://movie.douban.com/subject/22232939/","id":"22232939"},{"rating":{"max":10,"average":0,"stars":"00","min":0},"genres":["悬疑","惊悚"],"title":"玲珑井","casts":[{"alt":"https://movie.douban.com/celebrity/1329270/","avatars":{"small":"https://img3.doubanio.com/img/celebrity/small/1400230886.32.jpg","large":"https://img3.doubanio.com/img/celebrity/large/1400230886.32.jpg","medium":"https://img3.doubanio.com/img/celebrity/medium/1400230886.32.jpg"},"name":"宋睿","id":"1329270"},{"alt":"https://movie.douban.com/celebrity/1323524/","avatars":{"small":"https://img3.doubanio.com/img/celebrity/small/1450200716.95.jpg","large":"https://img3.doubanio.com/img/celebrity/large/1450200716.95.jpg","medium":"https://img3.doubanio.com/img/celebrity/medium/1450200716.95.jpg"},"name":"王良","id":"1323524"},{"alt":"https://movie.douban.com/celebrity/1341569/","avatars":{"small":"https://img3.doubanio.com/img/celebrity/small/1406089479.1.jpg","large":"https://img3.doubanio.com/img/celebrity/large/1406089479.1.jpg","medium":"https://img3.doubanio.com/img/celebrity/medium/1406089479.1.jpg"},"name":"罗翔","id":"1341569"}],"collect_count":3,"original_title":"玲珑井","subtype":"movie","directors":[{"alt":"https://movie.douban.com/celebrity/1323524/","avatars":{"small":"https://img3.doubanio.com/img/celebrity/small/1450200716.95.jpg","large":"https://img3.doubanio.com/img/celebrity/large/1450200716.95.jpg","medium":"https://img3.doubanio.com/img/celebrity/medium/1450200716.95.jpg"},"name":"王良","id":"1323524"}],"year":"2017","images":{"small":"https://img1.doubanio.com/view/movie_poster_cover/ipst/public/p2457901479.jpg","large":"https://img1.doubanio.com/view/movie_poster_cover/lpst/public/p2457901479.jpg","medium":"https://img1.doubanio.com/view/movie_poster_cover/spst/public/p2457901479.jpg"},"alt":"https://movie.douban.com/subject/26984234/","id":"26984234"},{"rating":{"max":10,"average":0,"stars":"00","min":0},"genres":["悬疑","恐怖"],"title":"夜半凶铃","casts":[{"alt":"https://movie.douban.com/celebrity/1324425/","avatars":{"small":"https://img1.doubanio.com/img/celebrity/small/1432631731.99.jpg","large":"https://img1.doubanio.com/img/celebrity/large/1432631731.99.jpg","medium":"https://img1.doubanio.com/img/celebrity/medium/1432631731.99.jpg"},"name":"刘青","id":"1324425"},{"alt":"https://movie.douban.com/celebrity/1317325/","avatars":{"small":"https://img3.doubanio.com/img/celebrity/small/39485.jpg","large":"https://img3.doubanio.com/img/celebrity/large/39485.jpg","medium":"https://img3.doubanio.com/img/celebrity/medium/39485.jpg"},"name":"李浩轩","id":"1317325"},{"alt":"https://movie.douban.com/celebrity/1339731/","avatars":{"small":"https://img3.doubanio.com/img/celebrity/small/1499164395.6.jpg","large":"https://img3.doubanio.com/img/celebrity/large/1499164395.6.jpg","medium":"https://img3.doubanio.com/img/celebrity/medium/1499164395.6.jpg"},"name":"白瑶","id":"1339731"}],"collect_count":9,"original_title":"夜半凶铃","subtype":"movie","directors":[{"alt":"https://movie.douban.com/celebrity/1376582/","avatars":{"small":"https://img1.doubanio.com/img/celebrity/small/1499243527.29.jpg","large":"https://img1.doubanio.com/img/celebrity/large/1499243527.29.jpg","medium":"https://img1.doubanio.com/img/celebrity/medium/1499243527.29.jpg"},"name":"李耀东","id":"1376582"}],"year":"2017","images":{"small":"https://img3.doubanio.com/view/movie_poster_cover/ipst/public/p2492324154.jpg","large":"https://img3.doubanio.com/view/movie_poster_cover/lpst/public/p2492324154.jpg","medium":"https://img3.doubanio.com/view/movie_poster_cover/spst/public/p2492324154.jpg"},"alt":"https://movie.douban.com/subject/27082116/","id":"27082116"},{"rating":{"max":10,"average":0,"stars":"00","min":0},"genres":["爱情","奇幻"],"title":"三生三世十里桃花","casts":[{"alt":"https://movie.douban.com/celebrity/1049732/","avatars":{"small":"https://img3.doubanio.com/img/celebrity/small/38640.jpg","large":"https://img3.doubanio.com/img/celebrity/large/38640.jpg","medium":"https://img3.doubanio.com/img/celebrity/medium/38640.jpg"},"name":"刘亦菲","id":"1049732"},{"alt":"https://movie.douban.com/celebrity/1276051/","avatars":{"small":"https://img3.doubanio.com/img/celebrity/small/1435567211.65.jpg","large":"https://img3.doubanio.com/img/celebrity/large/1435567211.65.jpg","medium":"https://img3.doubanio.com/img/celebrity/medium/1435567211.65.jpg"},"name":"杨洋","id":"1276051"},{"alt":"https://movie.douban.com/celebrity/1276171/","avatars":{"small":"https://img3.doubanio.com/img/celebrity/small/1370330521.5.jpg","large":"https://img3.doubanio.com/img/celebrity/large/1370330521.5.jpg","medium":"https://img3.doubanio.com/img/celebrity/medium/1370330521.5.jpg"},"name":"罗晋","id":"1276171"}],"collect_count":2335,"original_title":"三生三世十里桃花","subtype":"movie","directors":[{"alt":"https://movie.douban.com/celebrity/1274347/","avatars":{"small":"https://img1.doubanio.com/img/celebrity/small/17758.jpg","large":"https://img1.doubanio.com/img/celebrity/large/17758.jpg","medium":"https://img1.doubanio.com/img/celebrity/medium/17758.jpg"},"name":"赵小丁","id":"1274347"},{"alt":"https://movie.douban.com/celebrity/1289344/","avatars":{"small":"https://img1.doubanio.com/img/celebrity/small/45049.jpg","large":"https://img1.doubanio.com/img/celebrity/large/45049.jpg","medium":"https://img1.doubanio.com/img/celebrity/medium/45049.jpg"},"name":"安东尼·拉默里纳拉","id":"1289344"}],"year":"2017","images":{"small":"https://img1.doubanio.com/view/movie_poster_cover/ipst/public/p2466328529.jpg","large":"https://img1.doubanio.com/view/movie_poster_cover/lpst/public/p2466328529.jpg","medium":"https://img1.doubanio.com/view/movie_poster_cover/spst/public/p2466328529.jpg"},"alt":"https://movie.douban.com/subject/25823277/","id":"25823277"},{"rating":{"max":10,"average":0,"stars":"00","min":0},"genres":["剧情","喜剧"],"title":"谁是球王","casts":[{"alt":"https://movie.douban.com/celebrity/1338185/","avatars":{"small":"https://img3.doubanio.com/img/celebrity/small/1393237473.93.jpg","large":"https://img3.doubanio.com/img/celebrity/large/1393237473.93.jpg","medium":"https://img3.doubanio.com/img/celebrity/medium/1393237473.93.jpg"},"name":"尹航","id":"1338185"},{"alt":"https://movie.douban.com/celebrity/1321741/","avatars":{"small":"https://img1.doubanio.com/img/celebrity/small/1466061885.29.jpg","large":"https://img1.doubanio.com/img/celebrity/large/1466061885.29.jpg","medium":"https://img1.doubanio.com/img/celebrity/medium/1466061885.29.jpg"},"name":"代旭","id":"1321741"},{"alt":"https://movie.douban.com/celebrity/1315443/","avatars":{"small":"https://img1.doubanio.com/img/celebrity/small/1435074101.27.jpg","large":"https://img1.doubanio.com/img/celebrity/large/1435074101.27.jpg","medium":"https://img1.doubanio.com/img/celebrity/medium/1435074101.27.jpg"},"name":"李晨浩","id":"1315443"}],"collect_count":29,"original_title":"谁是球王","subtype":"movie","directors":[{"alt":"https://movie.douban.com/celebrity/1324056/","avatars":{"small":"https://img3.doubanio.com/img/celebrity/small/1495086607.22.jpg","large":"https://img3.doubanio.com/img/celebrity/large/1495086607.22.jpg","medium":"https://img3.doubanio.com/img/celebrity/medium/1495086607.22.jpg"},"name":"裘仲维","id":"1324056"}],"year":"2017","images":{"small":"https://img3.doubanio.com/view/movie_poster_cover/ipst/public/p2469808920.jpg","large":"https://img3.doubanio.com/view/movie_poster_cover/lpst/public/p2469808920.jpg","medium":"https://img3.doubanio.com/view/movie_poster_cover/spst/public/p2469808920.jpg"},"alt":"https://movie.douban.com/subject/26958767/","id":"26958767"},{"rating":{"max":10,"average":6.8,"stars":"35","min":0},"genres":["剧情"],"title":"皮绳上的魂","casts":[{"alt":"https://movie.douban.com/celebrity/1362878/","avatars":{"small":"https://img1.doubanio.com/img/celebrity/small/1495517018.67.jpg","large":"https://img1.doubanio.com/img/celebrity/large/1495517018.67.jpg","medium":"https://img1.doubanio.com/img/celebrity/medium/1495517018.67.jpg"},"name":"金巴","id":"1362878"},{"alt":"https://movie.douban.com/celebrity/1376956/","avatars":{"small":"https://img3.doubanio.com/img/celebrity/small/1499769716.36.jpg","large":"https://img3.doubanio.com/img/celebrity/large/1499769716.36.jpg","medium":"https://img3.doubanio.com/img/celebrity/medium/1499769716.36.jpg"},"name":"曲尼次仁","id":"1376956"},{"alt":"https://movie.douban.com/celebrity/1376957/","avatars":{"small":"https://img3.doubanio.com/img/celebrity/small/1499769871.04.jpg","large":"https://img3.doubanio.com/img/celebrity/large/1499769871.04.jpg","medium":"https://img3.doubanio.com/img/celebrity/medium/1499769871.04.jpg"},"name":"夏诺.扎西敦珠","id":"1376957"}],"collect_count":463,"original_title":"皮绳上的魂","subtype":"movie","directors":[{"alt":"https://movie.douban.com/celebrity/1301697/","avatars":{"small":"https://img3.doubanio.com/img/celebrity/small/1356350729.21.jpg","large":"https://img3.doubanio.com/img/celebrity/large/1356350729.21.jpg","medium":"https://img3.doubanio.com/img/celebrity/medium/1356350729.21.jpg"},"name":"张杨","id":"1301697"}],"year":"2016","images":{"small":"https://img1.doubanio.com/view/movie_poster_cover/ipst/public/p2493512317.jpg","large":"https://img1.doubanio.com/view/movie_poster_cover/lpst/public/p2493512317.jpg","medium":"https://img1.doubanio.com/view/movie_poster_cover/spst/public/p2493512317.jpg"},"alt":"https://movie.douban.com/subject/26177735/","id":"26177735"},{"rating":{"max":10,"average":0,"stars":"00","min":0},"genres":["动作","历史","战争"],"title":"龙之战","casts":[{"alt":"https://movie.douban.com/celebrity/1274585/","avatars":{"small":"https://img3.doubanio.com/img/celebrity/small/5612.jpg","large":"https://img3.doubanio.com/img/celebrity/large/5612.jpg","medium":"https://img3.doubanio.com/img/celebrity/medium/5612.jpg"},"name":"刘佩琦","id":"1274585"},{"alt":"https://movie.douban.com/celebrity/1318973/","avatars":{"small":"https://img3.doubanio.com/img/celebrity/small/1490533079.73.jpg","large":"https://img3.doubanio.com/img/celebrity/large/1490533079.73.jpg","medium":"https://img3.doubanio.com/img/celebrity/medium/1490533079.73.jpg"},"name":"曹云金","id":"1318973"},{"alt":"https://movie.douban.com/celebrity/1342748/","avatars":{"small":"https://img3.doubanio.com/img/celebrity/small/1464930051.83.jpg","large":"https://img3.doubanio.com/img/celebrity/large/1464930051.83.jpg","medium":"https://img3.doubanio.com/img/celebrity/medium/1464930051.83.jpg"},"name":"罗昱焜","id":"1342748"}],"collect_count":36,"original_title":"龙之战","subtype":"movie","directors":[{"alt":"https://movie.douban.com/celebrity/1319184/","avatars":{"small":"https://img3.doubanio.com/img/celebrity/small/46010.jpg","large":"https://img3.doubanio.com/img/celebrity/large/46010.jpg","medium":"https://img3.doubanio.com/img/celebrity/medium/46010.jpg"},"name":"高峰","id":"1319184"}],"year":"2017","images":{"small":"https://img3.doubanio.com/view/movie_poster_cover/ipst/public/p2469843751.jpg","large":"https://img3.doubanio.com/view/movie_poster_cover/lpst/public/p2469843751.jpg","medium":"https://img3.doubanio.com/view/movie_poster_cover/spst/public/p2469843751.jpg"},"alt":"https://movie.douban.com/subject/26873799/","id":"26873799"},{"rating":{"max":10,"average":0,"stars":"00","min":0},"genres":["剧情","运动"],"title":"我是马布里","casts":[{"alt":"https://movie.douban.com/celebrity/1173696/","avatars":{"small":"https://img1.doubanio.com/img/celebrity/small/42237.jpg","large":"https://img1.doubanio.com/img/celebrity/large/42237.jpg","medium":"https://img1.doubanio.com/img/celebrity/medium/42237.jpg"},"name":"斯蒂芬·马布里","id":"1173696"},{"alt":"https://movie.douban.com/celebrity/1028237/","avatars":{"small":"https://img3.doubanio.com/img/celebrity/small/28356.jpg","large":"https://img3.doubanio.com/img/celebrity/large/28356.jpg","medium":"https://img3.doubanio.com/img/celebrity/medium/28356.jpg"},"name":"吴尊","id":"1028237"},{"alt":"https://movie.douban.com/celebrity/1274825/","avatars":{"small":"https://img3.doubanio.com/img/celebrity/small/21352.jpg","large":"https://img3.doubanio.com/img/celebrity/large/21352.jpg","medium":"https://img3.doubanio.com/img/celebrity/medium/21352.jpg"},"name":"何冰","id":"1274825"}],"collect_count":111,"original_title":"我是马布里","subtype":"movie","directors":[{"alt":"https://movie.douban.com/celebrity/1335623/","avatars":{"small":"https://img3.doubanio.com/img/celebrity/small/1382696083.12.jpg","large":"https://img3.doubanio.com/img/celebrity/large/1382696083.12.jpg","medium":"https://img3.doubanio.com/img/celebrity/medium/1382696083.12.jpg"},"name":"杨子","id":"1335623"}],"year":"2017","images":{"small":"https://img3.doubanio.com/view/movie_poster_cover/ipst/public/p2455805686.jpg","large":"https://img3.doubanio.com/view/movie_poster_cover/lpst/public/p2455805686.jpg","medium":"https://img3.doubanio.com/view/movie_poster_cover/spst/public/p2455805686.jpg"},"alt":"https://movie.douban.com/subject/25903033/","id":"25903033"},{"rating":{"max":10,"average":0,"stars":"00","min":0},"genres":["动画","奇幻","冒险"],"title":"玩偶奇兵","casts":[{"alt":"https://movie.douban.com/celebrity/1328395/","avatars":{"small":"https://img1.doubanio.com/img/celebrity/small/1496307914.59.jpg","large":"https://img1.doubanio.com/img/celebrity/large/1496307914.59.jpg","medium":"https://img1.doubanio.com/img/celebrity/medium/1496307914.59.jpg"},"name":"严丽祯","id":"1328395"},{"alt":"https://movie.douban.com/celebrity/1326522/","avatars":{"small":"https://img3.doubanio.com/img/celebrity/small/1498555670.36.jpg","large":"https://img3.doubanio.com/img/celebrity/large/1498555670.36.jpg","medium":"https://img3.doubanio.com/img/celebrity/medium/1498555670.36.jpg"},"name":"李晔","id":"1326522"},{"alt":"https://movie.douban.com/celebrity/1374803/","avatars":{"small":"https://img3.doubanio.com/img/celebrity/small/1496307969.11.jpg","large":"https://img3.doubanio.com/img/celebrity/large/1496307969.11.jpg","medium":"https://img3.doubanio.com/img/celebrity/medium/1496307969.11.jpg"},"name":"王衡","id":"1374803"}],"collect_count":7,"original_title":"玩偶奇兵","subtype":"movie","directors":[{"alt":"https://movie.douban.com/celebrity/1374801/","avatars":{"small":"https://img1.doubanio.com/img/celebrity/small/1496307826.17.jpg","large":"https://img1.doubanio.com/img/celebrity/large/1496307826.17.jpg","medium":"https://img1.doubanio.com/img/celebrity/medium/1496307826.17.jpg"},"name":"申宇","id":"1374801"},{"alt":"https://movie.douban.com/celebrity/1336918/","avatars":{"small":"https://img1.doubanio.com/img/celebrity/small/1496307805.39.jpg","large":"https://img1.doubanio.com/img/celebrity/large/1496307805.39.jpg","medium":"https://img1.doubanio.com/img/celebrity/medium/1496307805.39.jpg"},"name":"黄燕","id":"1336918"}],"year":"2017","images":{"small":"https://img3.doubanio.com/view/movie_poster_cover/ipst/public/p2492765331.jpg","large":"https://img3.doubanio.com/view/movie_poster_cover/lpst/public/p2492765331.jpg","medium":"https://img3.doubanio.com/view/movie_poster_cover/spst/public/p2492765331.jpg"},"alt":"https://movie.douban.com/subject/27026033/","id":"27026033"},{"rating":{"max":10,"average":0,"stars":"00","min":0},"genres":["动作","战争","动画"],"title":"大象林旺之一炮成名","casts":[{"alt":"https://movie.douban.com/celebrity/1326029/","avatars":{"small":"https://img3.doubanio.com/img/celebrity/small/1497931434.53.jpg","large":"https://img3.doubanio.com/img/celebrity/large/1497931434.53.jpg","medium":"https://img3.doubanio.com/img/celebrity/medium/1497931434.53.jpg"},"name":"宋晓宇","id":"1326029"},{"alt":"https://movie.douban.com/celebrity/1375891/","avatars":{"small":"https://img3.doubanio.com/img/celebrity/small/1497931521.94.jpg","large":"https://img3.doubanio.com/img/celebrity/large/1497931521.94.jpg","medium":"https://img3.doubanio.com/img/celebrity/medium/1497931521.94.jpg"},"name":"李垚","id":"1375891"},{"alt":"https://movie.douban.com/celebrity/1375892/","avatars":{"small":"https://img1.doubanio.com/img/celebrity/small/1497931601.49.jpg","large":"https://img1.doubanio.com/img/celebrity/large/1497931601.49.jpg","medium":"https://img1.doubanio.com/img/celebrity/medium/1497931601.49.jpg"},"name":"徐炜","id":"1375892"}],"collect_count":8,"original_title":"大象林旺之一炮成名","subtype":"movie","directors":[{"alt":"https://movie.douban.com/celebrity/1375890/","avatars":{"small":"https://img1.doubanio.com/img/celebrity/small/1498455064.89.jpg","large":"https://img1.doubanio.com/img/celebrity/large/1498455064.89.jpg","medium":"https://img1.doubanio.com/img/celebrity/medium/1498455064.89.jpg"},"name":"李涛歌","id":"1375890"}],"year":"2017","images":{"small":"https://img3.doubanio.com/view/movie_poster_cover/ipst/public/p2492308445.jpg","large":"https://img3.doubanio.com/view/movie_poster_cover/lpst/public/p2492308445.jpg","medium":"https://img3.doubanio.com/view/movie_poster_cover/spst/public/p2492308445.jpg"},"alt":"https://movie.douban.com/subject/27068480/","id":"27068480"},{"rating":{"max":10,"average":0,"stars":"00","min":0},"genres":["悬疑"],"title":"原罪的羔羊","casts":[{"alt":"https://movie.douban.com/celebrity/1377140/","avatars":{"small":"https://img3.doubanio.com/img/celebrity/small/1499943601.01.jpg","large":"https://img3.doubanio.com/img/celebrity/large/1499943601.01.jpg","medium":"https://img3.doubanio.com/img/celebrity/medium/1499943601.01.jpg"},"name":"周鹏雨","id":"1377140"},{"alt":"https://movie.douban.com/celebrity/1377141/","avatars":{"small":"https://img3.doubanio.com/img/celebrity/small/1499943578.21.jpg","large":"https://img3.doubanio.com/img/celebrity/large/1499943578.21.jpg","medium":"https://img3.doubanio.com/img/celebrity/medium/1499943578.21.jpg"},"name":"穆建荣","id":"1377141"},{"alt":"https://movie.douban.com/celebrity/1377139/","avatars":{"small":"https://img1.doubanio.com/f/movie/ca527386eb8c4e325611e22dfcb04cc116d6b423/pics/movie/celebrity-default-small.png","large":"https://img3.doubanio.com/f/movie/63acc16ca6309ef191f0378faf793d1096a3e606/pics/movie/celebrity-default-large.png","medium":"https://img1.doubanio.com/f/movie/8dd0c794499fe925ae2ae89ee30cd225750457b4/pics/movie/celebrity-default-medium.png"},"name":"陈泽帆","id":"1377139"}],"collect_count":3,"original_title":"原罪的羔羊","subtype":"movie","directors":[{"alt":"https://movie.douban.com/celebrity/1377138/","avatars":{"small":"https://img3.doubanio.com/img/celebrity/small/1500260084.21.jpg","large":"https://img3.doubanio.com/img/celebrity/large/1500260084.21.jpg","medium":"https://img3.doubanio.com/img/celebrity/medium/1500260084.21.jpg"},"name":"闫国喜","id":"1377138"}],"year":"2017","images":{"small":"https://img3.doubanio.com/view/movie_poster_cover/ipst/public/p2492870282.jpg","large":"https://img3.doubanio.com/view/movie_poster_cover/lpst/public/p2492870282.jpg","medium":"https://img3.doubanio.com/view/movie_poster_cover/spst/public/p2492870282.jpg"},"alt":"https://movie.douban.com/subject/27088552/","id":"27088552"},{"rating":{"max":10,"average":0,"stars":"00","min":0},"genres":["惊悚","恐怖"],"title":"诡井","casts":[{"alt":"https://movie.douban.com/celebrity/1349114/","avatars":{"small":"https://img3.doubanio.com/img/celebrity/small/1448033220.72.jpg","large":"https://img3.doubanio.com/img/celebrity/large/1448033220.72.jpg","medium":"https://img3.doubanio.com/img/celebrity/medium/1448033220.72.jpg"},"name":"彭禺厶","id":"1349114"},{"alt":"https://movie.douban.com/celebrity/1371277/","avatars":{"small":"https://img3.doubanio.com/img/celebrity/small/GgYl_I9a2Iscel_avatar_uploaded1490756493.05.jpg","large":"https://img3.doubanio.com/img/celebrity/large/GgYl_I9a2Iscel_avatar_uploaded1490756493.05.jpg","medium":"https://img3.doubanio.com/img/celebrity/medium/GgYl_I9a2Iscel_avatar_uploaded1490756493.05.jpg"},"name":"王萌","id":"1371277"},{"alt":"https://movie.douban.com/celebrity/1329440/","avatars":{"small":"https://img3.doubanio.com/img/celebrity/small/1369633357.44.jpg","large":"https://img3.doubanio.com/img/celebrity/large/1369633357.44.jpg","medium":"https://img3.doubanio.com/img/celebrity/medium/1369633357.44.jpg"},"name":"周凯文","id":"1329440"}],"collect_count":0,"original_title":"诡井","subtype":"movie","directors":[{"alt":"https://movie.douban.com/celebrity/1377598/","avatars":{"small":"https://img1.doubanio.com/f/movie/ca527386eb8c4e325611e22dfcb04cc116d6b423/pics/movie/celebrity-default-small.png","large":"https://img3.doubanio.com/f/movie/63acc16ca6309ef191f0378faf793d1096a3e606/pics/movie/celebrity-default-large.png","medium":"https://img1.doubanio.com/f/movie/8dd0c794499fe925ae2ae89ee30cd225750457b4/pics/movie/celebrity-default-medium.png"},"name":"常杨","id":"1377598"}],"year":"2017","images":{"small":"https://img3.doubanio.com/view/movie_poster_cover/ipst/public/p2493299281.jpg","large":"https://img3.doubanio.com/view/movie_poster_cover/lpst/public/p2493299281.jpg","medium":"https://img3.doubanio.com/view/movie_poster_cover/spst/public/p2493299281.jpg"},"alt":"https://movie.douban.com/subject/27091323/","id":"27091323"},{"rating":{"max":10,"average":0,"stars":"00","min":0},"genres":["动作","犯罪","悬疑"],"title":"心理罪","casts":[{"alt":"https://movie.douban.com/celebrity/1007401/","avatars":{"small":"https://img3.doubanio.com/img/celebrity/small/1454644679.84.jpg","large":"https://img3.doubanio.com/img/celebrity/large/1454644679.84.jpg","medium":"https://img3.doubanio.com/img/celebrity/medium/1454644679.84.jpg"},"name":"廖凡","id":"1007401"},{"alt":"https://movie.douban.com/celebrity/1314140/","avatars":{"small":"https://img1.doubanio.com/img/celebrity/small/1403196522.98.jpg","large":"https://img1.doubanio.com/img/celebrity/large/1403196522.98.jpg","medium":"https://img1.doubanio.com/img/celebrity/medium/1403196522.98.jpg"},"name":"李易峰","id":"1314140"},{"alt":"https://movie.douban.com/celebrity/1315477/","avatars":{"small":"https://img3.doubanio.com/img/celebrity/small/1483453357.64.jpg","large":"https://img3.doubanio.com/img/celebrity/large/1483453357.64.jpg","medium":"https://img3.doubanio.com/img/celebrity/medium/1483453357.64.jpg"},"name":"万茜","id":"1315477"}],"collect_count":1441,"original_title":"心理罪","subtype":"movie","directors":[{"alt":"https://movie.douban.com/celebrity/1317475/","avatars":{"small":"https://img3.doubanio.com/img/celebrity/small/1446390191.61.jpg","large":"https://img3.doubanio.com/img/celebrity/large/1446390191.61.jpg","medium":"https://img3.doubanio.com/img/celebrity/medium/1446390191.61.jpg"},"name":"谢东燊","id":"1317475"}],"year":"2017","images":{"small":"https://img3.doubanio.com/view/movie_poster_cover/ipst/public/p2492869971.jpg","large":"https://img3.doubanio.com/view/movie_poster_cover/lpst/public/p2492869971.jpg","medium":"https://img3.doubanio.com/view/movie_poster_cover/spst/public/p2492869971.jpg"},"alt":"https://movie.douban.com/subject/26698000/","id":"26698000"},{"rating":{"max":10,"average":0,"stars":"00","min":0},"genres":["动作","冒险"],"title":"侠盗联盟","casts":[{"alt":"https://movie.douban.com/celebrity/1054424/","avatars":{"small":"https://img3.doubanio.com/img/celebrity/small/1378956633.91.jpg","large":"https://img3.doubanio.com/img/celebrity/large/1378956633.91.jpg","medium":"https://img3.doubanio.com/img/celebrity/medium/1378956633.91.jpg"},"name":"刘德华","id":"1054424"},{"alt":"https://movie.douban.com/celebrity/1138320/","avatars":{"small":"https://img1.doubanio.com/img/celebrity/small/1268.jpg","large":"https://img1.doubanio.com/img/celebrity/large/1268.jpg","medium":"https://img1.doubanio.com/img/celebrity/medium/1268.jpg"},"name":"舒淇","id":"1138320"},{"alt":"https://movie.douban.com/celebrity/1016668/","avatars":{"small":"https://img3.doubanio.com/img/celebrity/small/146.jpg","large":"https://img3.doubanio.com/img/celebrity/large/146.jpg","medium":"https://img3.doubanio.com/img/celebrity/medium/146.jpg"},"name":"张静初","id":"1016668"}],"collect_count":45,"original_title":"俠盜聯盟","subtype":"movie","directors":[{"alt":"https://movie.douban.com/celebrity/1023278/","avatars":{"small":"https://img3.doubanio.com/img/celebrity/small/20775.jpg","large":"https://img3.doubanio.com/img/celebrity/large/20775.jpg","medium":"https://img3.doubanio.com/img/celebrity/medium/20775.jpg"},"name":"冯德伦","id":"1023278"}],"year":"2017","images":{"small":"https://img3.doubanio.com/view/movie_poster_cover/ipst/public/p2493127222.jpg","large":"https://img3.doubanio.com/view/movie_poster_cover/lpst/public/p2493127222.jpg","medium":"https://img3.doubanio.com/view/movie_poster_cover/spst/public/p2493127222.jpg"},"alt":"https://movie.douban.com/subject/25858758/","id":"25858758"},{"rating":{"max":10,"average":0,"stars":"00","min":0},"genres":["喜剧","动作","爱情"],"title":"鲛珠传","casts":[{"alt":"https://movie.douban.com/celebrity/1341187/","avatars":{"small":"https://img1.doubanio.com/img/celebrity/small/bA7b3PGSjgMcel_avatar_uploaded1404566496.8.jpg","large":"https://img1.doubanio.com/img/celebrity/large/bA7b3PGSjgMcel_avatar_uploaded1404566496.8.jpg","medium":"https://img1.doubanio.com/img/celebrity/medium/bA7b3PGSjgMcel_avatar_uploaded1404566496.8.jpg"},"name":"王大陆","id":"1341187"},{"alt":"https://movie.douban.com/celebrity/1353578/","avatars":{"small":"https://img1.doubanio.com/img/celebrity/small/1458201743.67.jpg","large":"https://img1.doubanio.com/img/celebrity/large/1458201743.67.jpg","medium":"https://img1.doubanio.com/img/celebrity/medium/1458201743.67.jpg"},"name":"张天爱","id":"1353578"},{"alt":"https://movie.douban.com/celebrity/1031194/","avatars":{"small":"https://img3.doubanio.com/img/celebrity/small/32971.jpg","large":"https://img3.doubanio.com/img/celebrity/large/32971.jpg","medium":"https://img3.doubanio.com/img/celebrity/medium/32971.jpg"},"name":"任达华","id":"1031194"}],"collect_count":131,"original_title":"鲛珠传","subtype":"movie","directors":[{"alt":"https://movie.douban.com/celebrity/1321964/","avatars":{"small":"https://img3.doubanio.com/img/celebrity/small/1497492672.66.jpg","large":"https://img3.doubanio.com/img/celebrity/large/1497492672.66.jpg","medium":"https://img3.doubanio.com/img/celebrity/medium/1497492672.66.jpg"},"name":"杨磊","id":"1321964"}],"year":"2017","images":{"small":"https://img3.doubanio.com/view/movie_poster_cover/ipst/public/p2493306442.jpg","large":"https://img3.doubanio.com/view/movie_poster_cover/lpst/public/p2493306442.jpg","medium":"https://img3.doubanio.com/view/movie_poster_cover/spst/public/p2493306442.jpg"},"alt":"https://movie.douban.com/subject/25857966/","id":"25857966"},{"rating":{"max":10,"average":0,"stars":"00","min":0},"genres":["纪录片"],"title":"地球：神奇的一天","casts":[{"alt":"https://movie.douban.com/celebrity/1054531/","avatars":{"small":"https://img3.doubanio.com/img/celebrity/small/694.jpg","large":"https://img3.doubanio.com/img/celebrity/large/694.jpg","medium":"https://img3.doubanio.com/img/celebrity/medium/694.jpg"},"name":"成龙","id":"1054531"},{"alt":"https://movie.douban.com/celebrity/1053617/","avatars":{"small":"https://img3.doubanio.com/img/celebrity/small/543.jpg","large":"https://img3.doubanio.com/img/celebrity/large/543.jpg","medium":"https://img3.doubanio.com/img/celebrity/medium/543.jpg"},"name":"罗伯特·雷德福","id":"1053617"}],"collect_count":7,"original_title":"Earth：One Amazing Day","subtype":"movie","directors":[{"alt":"https://movie.douban.com/celebrity/1281735/","avatars":{"small":"https://img1.doubanio.com/f/movie/ca527386eb8c4e325611e22dfcb04cc116d6b423/pics/movie/celebrity-default-small.png","large":"https://img3.doubanio.com/f/movie/63acc16ca6309ef191f0378faf793d1096a3e606/pics/movie/celebrity-default-large.png","medium":"https://img1.doubanio.com/f/movie/8dd0c794499fe925ae2ae89ee30cd225750457b4/pics/movie/celebrity-default-medium.png"},"name":"理查德·戴尔","id":"1281735"},{"alt":"https://movie.douban.com/celebrity/1300561/","avatars":{"small":"https://img1.doubanio.com/img/celebrity/small/1499912397.39.jpg","large":"https://img1.doubanio.com/img/celebrity/large/1499912397.39.jpg","medium":"https://img1.doubanio.com/img/celebrity/medium/1499912397.39.jpg"},"name":"彼得·韦柏 ","id":"1300561"},{"alt":"https://movie.douban.com/celebrity/1312984/","avatars":{"small":"https://img3.doubanio.com/img/celebrity/small/14524.jpg","large":"https://img3.doubanio.com/img/celebrity/large/14524.jpg","medium":"https://img3.doubanio.com/img/celebrity/medium/14524.jpg"},"name":"范立欣","id":"1312984"}],"year":"2017","images":{"small":"https://img1.doubanio.com/view/movie_poster_cover/ipst/public/p2493261459.jpg","large":"https://img1.doubanio.com/view/movie_poster_cover/lpst/public/p2493261459.jpg","medium":"https://img1.doubanio.com/view/movie_poster_cover/spst/public/p2493261459.jpg"},"alt":"https://movie.douban.com/subject/26647876/","id":"26647876"}]}